{
   "places" : [
      {
         "title" : "Title",
         "image" : "http://maps.gstatic.com/mapfiles/place_api/icons/restaurant-71.png",
         "description" : "Description",
         "categories" : [ "restaurant", "food", "establishment" ],
         "location" : "Budapest, Hungary"
         "lat" : 0,
         "lon" : 0
      },
      {
         "title" : "Title",
         "image" : "http://maps.gstatic.com/mapfiles/place_api/icons/restaurant-71.png",
         "description" : "Description",
         "categories" : [ "restaurant", "food", "establishment" ],
         "location" : "Budapest, Hungary"
         "lat" : 0,
         "lon" : 0
      },
      {
         "title" : "Title",
         "image" : "http://maps.gstatic.com/mapfiles/place_api/icons/restaurant-71.png",
         "description" : "Description",
         "categories" : [ "restaurant", "food", "establishment" ],
         "location" : "Budapest, Hungary"
         "lat" : 0,
         "lon" : 0
      }
   ],
   "status" : "OK"
}